MANIFEST.in
README.md
setup.cfg
setup.py
dirtyedit/__init__.py
dirtyedit/admin.py
dirtyedit/apps.py
dirtyedit/conf.py
dirtyedit/forms.py
dirtyedit/models.py
dirtyedit/tests.py
dirtyedit/utils.py
dirtyedit/migrations/0001_initial.py
dirtyedit/migrations/__init__.py
dirtyedit/templates/admin/dirtyedit/change_form.html
dirtyedit/templates/admin/dirtyedit/change_list.html
dirtyedit/templates/admin/dirtyedit/includes/fieldset.html
dirtyedit/templates/codemirror2/codemirror_script.html
dirtyedit/templates/reversion/change_list.html
django_dirtyedit.egg-info/PKG-INFO
django_dirtyedit.egg-info/SOURCES.txt
django_dirtyedit.egg-info/dependency_links.txt
django_dirtyedit.egg-info/not-zip-safe
django_dirtyedit.egg-info/requires.txt
django_dirtyedit.egg-info/top_level.txt