Metadata-Version: 1.1
Name: django-dirtyedit
Version: 0.3
Summary:  Django application to edit files from the admin interface
Home-page: https://github.com/synw/django-dirtyedit
Author: synw
Author-email: synwe@yahoo.com
License: UNKNOWN
Download-URL: https://github.com/synw/django-dirtyedit/releases/tag/0.3
Keywords: django,editor
Platform: UNKNOWN
Classifier: Development Status :: 3 - Alpha
Classifier: Framework :: Django :: 1.8
Classifier: Intended Audience :: Developers
Classifier: License :: OSI Approved :: MIT License
Classifier: Programming Language :: Python :: 2.7
